process_manager/__init__.py
process_manager/__main__.py
process_manager/manager.py
process_manager/process_list.py
process_manager/view_base.py
process_manager/view_table.py
process_manager/view_tree.py
gui_process_manager-0.2.1.dist-info/METADATA
gui_process_manager-0.2.1.dist-info/WHEEL
gui_process_manager-0.2.1.dist-info/RECORD
