Metadata-Version: 2.3
Name: gui-process-manager
Version: 0.2.1
Summary: This is a tool that provides a GUI to manage processes and process trees.
Author: 黎明10071868
Author-email: li.ming23@zte.com.cn
Requires-Python: >=3.12
Classifier: Programming Language :: Python :: 3
Classifier: Programming Language :: Python :: 3.12
Classifier: Programming Language :: Python :: 3.13
Requires-Dist: ming-formatter (>=0.1.1,<0.2.0)
Requires-Dist: psutil (>=7.0.0,<8.0.0)
Requires-Dist: pyqt6 (>=6.9.1,<7.0.0)
